[
  {
    "ContainingType": "webapisimulationproduct.Controllers.ProductController",
    "Method": "GetAllProducts",
    "RelativePath": "api/Product",
    "HttpMethod": "GET",
    "IsController": true,
    "Order": 0,
    "Parameters": [],
    "ReturnTypes": [
      {
        "Type": "System.Collections.Generic.IEnumerable\u00601[[coresimulation.DTOs.ProductDto, coresimulation, Version=1.0.0.0, Culture=neutral, PublicKeyToken=null]]",
        "MediaTypes": [
          "text/plain",
          "application/json",
          "text/json"
        ],
        "StatusCode": 200
      }
    ]
  },
  {
    "ContainingType": "webapisimulationproduct.Controllers.ProductController",
    "Method": "GetProductById",
    "RelativePath": "api/Product/{id}",
    "HttpMethod": "GET",
    "IsController": true,
    "Order": 0,
    "Parameters": [
      {
        "Name": "id",
        "Type": "System.Int32",
        "IsRequired": true
      }
    ],
    "ReturnTypes": [
      {
        "Type": "coresimulation.DTOs.ProductDto",
        "MediaTypes": [
          "text/plain",
          "application/json",
          "text/json"
        ],
        "StatusCode": 200
      }
    ]
  },
  {
    "ContainingType": "coresimulation.Controllers.ProductCatalogController",
    "Method": "CreateProduct",
    "RelativePath": "api/ProductCatalog",
    "HttpMethod": "POST",
    "IsController": true,
    "Order": 0,
    "Parameters": [
      {
        "Name": "dto",
        "Type": "coresimulation.DTOs.ProductCreateDto",
        "IsRequired": true
      }
    ],
    "ReturnTypes": []
  },
  {
    "ContainingType": "webapisimulationproduct.Controllers.UploadController",
    "Method": "Upload",
    "RelativePath": "api/Upload",
    "HttpMethod": "POST",
    "IsController": true,
    "Order": 0,
    "Parameters": [
      {
        "Name": "formFile",
        "Type": "Microsoft.AspNetCore.Http.IFormFile",
        "IsRequired": false
      }
    ],
    "ReturnTypes": []
  },
  {
    "ContainingType": "webapisimulationproduct.Controllers.UploadController",
    "Method": "Download",
    "RelativePath": "api/Upload/downloaduploadedfile/{filename}",
    "HttpMethod": "GET",
    "IsController": true,
    "Order": 0,
    "Parameters": [
      {
        "Name": "filename",
        "Type": "System.String",
        "IsRequired": true
      }
    ],
    "ReturnTypes": []
  }
]